rlglue/__init__.py
rlglue/agent.py
rlglue/environment.py
rlglue/py.typed
rlglue/rl_glue.py
rlglue_andnp-2.0.1.dist-info/METADATA
rlglue_andnp-2.0.1.dist-info/WHEEL
rlglue_andnp-2.0.1.dist-info/RECORD
